tap_buttondown/__init__.py
tap_buttondown-0.3.0.dist-info/WHEEL
tap_buttondown-0.3.0.dist-info/entry_points.txt
tap_buttondown-0.3.0.dist-info/METADATA
tap_buttondown-0.3.0.dist-info/RECORD
