Metadata-Version: 2.3
Name: tap-buttondown
Version: 0.3.0
Summary: Singer.io tap for extracting data from the buttondown API
Author: Andrew Jones
Author-email: Andrew Jones <andrew@andrew-jones.com>
License: MIT License
Classifier: License :: OSI Approved :: Apache Software License
Classifier: Programming Language :: Python :: 3
Classifier: Programming Language :: Python :: 3.8
Requires-Dist: singer-python>=5.13.0
Requires-Dist: requests>=2.31.0
Requires-Dist: python-dateutil>=2.8.2
Requires-Dist: pytest>=7.0.0 ; extra == 'dev'
Requires-Dist: pytest-mock>=3.10.0 ; extra == 'dev'
Requires-Python: >=3.8
Project-URL: Homepage, https://github.com/andrewjones/tap-buttondown
Provides-Extra: dev
